[
    { "kategorie": "hersteller", "name": "Intel" },
    { "kategorie": "hersteller", "name": "AMD" },
    { "kategorie": "cpu", "name": "Intel Core i5-13600K", "hersteller": "Intel", "socket": "LGA1700" },
    { "kategorie": "cpu", "name": "AMD Ryzen 5 7600X", "hersteller": "AMD", "socket": "AM5" },
    { "kategorie": "mainboard", "name": "ASUS Z790-F", "kompatibel_mit": ["LGA1700"] },
    { "kategorie": "mainboard", "name": "MSI B650 Tomahawk", "kompatibel_mit": ["AM5"] },
    { "kategorie": "ram", "name": "16GB DDR5-6000 G.Skill" },
    { "kategorie": "ram", "name": "32GB DDR5-6000 Corsair" },
    { "kategorie": "nvme", "name": "1TB Samsung 980 Pro" },
    { "kategorie": "nvme", "name": "2TB WD Black SN850X" },
    { "kategorie": "grafikkarte", "name": "NVIDIA RTX 4070" },
    { "kategorie": "grafikkarte", "name": "AMD Radeon RX 7800 XT" }
    { "kategorie": "cpu", "name": "Intel Core i7-13700K", "hersteller": "Intel", "socket": "LGA1700" },
    { "kategorie": "cpu", "name": "AMD Ryzen 7 7700X", "hersteller": "AMD", "socket": "AM5" },
    { "kategorie": "mainboard", "name": "GIGABYTE Z790UD", "kompatibel_mit": ["LGA1700"] },
    { "kategorie": "mainboard", "name": "ASrock X670E Taichi", "kompatibel_mit": ["AM5"] },
    { "kategorie": "ram", "name": "64GB DDR5-6000 KINGSTON" },
    { "kategorie": "ram", "name": "32GB DDR5-6000 Crucial" },
    { "kategorie": "nvme", "name": "1TB Samsung 990 Pro" },
    { "kategorie": "nvme", "name": "4TB WD Black SN850X" },
    { "kategorie": "grafikkarte", "name": "NVIDIA RTX 4080" },
    { "kategorie": "grafikkarte", "name": "AMD Radeon RX 7900 XT" }
]
